voicetools/__init__.py
voicetools/api.py
voicetools/clients.py
voicetools/constants.py
voicetools/exceptions.py
voicetools/utils.py
voicetools-0.0.1.dist-info/DESCRIPTION.rst
voicetools-0.0.1.dist-info/METADATA
voicetools-0.0.1.dist-info/RECORD
voicetools-0.0.1.dist-info/WHEEL
voicetools-0.0.1.dist-info/metadata.json
voicetools-0.0.1.dist-info/pbr.json
voicetools-0.0.1.dist-info/top_level.txt
voicetools-0.0.1.dist-info/zip-safe
